Projects/Schematic_Design_and_Analysis_of_an_8-Word_8-Bit_Static_RAM_with_6T_Storage_Cells_using_SKY130PDK/assets/HDL_description/sram.v
module sram(
    input en,
    input ysw,ysr,
    input [2:0] add,
    input [7:0] din,
    output reg [7:0] dout
);

    reg [7:0] ram [7:0];

    always @(posedge en) begin
      if(ysw)
        ram[add] <= din;
      else if(ysr)
        dout <= ram[add];
      else
        dout <= 8'bxxxxxxxx;
    end

endmodule

Projects/Schematic_Design_and_Analysis_of_an_8-Word_8-Bit_Static_RAM_with_6T_Storage_Cells_using_SKY130PDK/assets/HDL_description/sram_tb.v
`timescale 1ns/1ps
module tb;
    reg en,ysw,ysr;
    reg [2:0] add;
    reg [7:0] din;

    wire [7:0] dout;

    sram inst1 (
        .en(en),
        .ysw(ysw),
        .ysr(ysr),
        .add(add),
        .din(din),
        .dout(dout)
    );

    initial begin
        en = 0;
        forever #5 en =~en;
    end
    initial begin
        $dumpfile("sram_gtk.vcd");$dumpvars();
    end

    initial begin
        add = 3'bzzz;
        din = 8'bzzzzzzzz;
        ysw = 1'b1;
        #5 add = 3'b000; 
        din = 8'b10010111;
        #10 add = 3'b001; 
        din = 8'b11111001;
        #10 add = 3'b010; 
        din = 8'b10000001;
        #10 add = 3'b011; 
        din = 8'b10011001;
        #10 din =8'bxxxxxxxx;
        ysw = 1'b0;
        ysr = 1'b1;
        add = 3'b000;
        #10 add = 3'b001;
        #10 add = 3'b010;
        #10 add = 3'b011;
        #10 $finish;
    end
    
endmodule

Projects/Schematic_Design_and_Analysis_of_an_8-Word_8-Bit_Static_RAM_with_6T_Storage_Cells_using_SKY130PDK/assets/HDL_description/sram_gtk.vcd
$date
	Thu Jul 18 20:04:11 2024
$end
$version
	Icarus Verilog
$end
$timescale
	1ps
$end
$scope module tb $end
$var wire 8 ! dout [7:0] $end
$var reg 3 " add [2:0] $end
$var reg 8 # din [7:0] $end
$var reg 1 $ en $end
$var reg 1 % ysr $end
$var reg 1 & ysw $end
$scope module inst1 $end
$var wire 3 ' add [2:0] $end
$var wire 8 ( din [7:0] $end
$var wire 1 $ en $end
$var wire 1 % ysr $end
$var wire 1 & ysw $end
$var reg 8 ) dout [7:0] $end
$upscope $end
$upscope $end
$enddefinitions $end
$comment Show the parameter values. $end
$dumpall
$end
#0
$dumpvars
bx )
bz (
bz '
1&
x%
0$
bz #
bz "
bx !
$end
#5000
b10010111 #
b10010111 (
b0 "
b0 '
1$
#10000
0$
#15000
1$
b11111001 #
b11111001 (
b1 "
b1 '
#20000
0$
#25000
1$
b10000001 #
b10000001 (
b10 "
b10 '
#30000
0$
#35000
1$
b10011001 #
b10011001 (
b11 "
b11 '
#40000
0$
#45000
b10010111 !
b10010111 )
1$
b0 "
b0 '
1%
0&
bx #
bx (
#50000
0$
#55000
b11111001 !
b11111001 )
1$
b1 "
b1 '
#60000
0$
#65000
b10000001 !
b10000001 )
1$
b10 "
b10 '
#70000
0$
#75000
b10011001 !
b10011001 )
1$
b11 "
b11 '
#80000
0$
#85000
1$
